[1,["d4M8BrFu1D+5dQFWFa0Y9K@6c48a"],["_textureSource"],["cc.SpriteFrame"],0,[{"name":"pic_hot","rect":{"x":0,"y":0,"width":103,"height":104},"offset":{"x":-0.5,"y":0},"originalSize":{"width":104,"height":104},"rotated":false,"capInsets":[0,0,0,0],"vertices":{"rawPosition":[-51.5,-52,0,51.5,-52,0,-51.5,52,0,51.5,52,0],"indexes":[0,1,2,2,1,3],"uv":[0,104,103,104,0,0,103,0],"nuv":[0,0,0.9903846153846154,0,0,1,0.9903846153846154,1],"minPos":{"x":-51.5,"y":-52,"z":0},"maxPos":{"x":51.5,"y":52,"z":0}},"packable":true,"pixelsToUnit":100,"pivot":{"x":0.5,"y":0.5},"meshType":0}],[0],0,[0],[0],[0]]
